configfile/__init__.py
configfile-1.2.4.dist-info/LICENSE
configfile-1.2.4.dist-info/METADATA
configfile-1.2.4.dist-info/WHEEL
configfile-1.2.4.dist-info/top_level.txt
configfile-1.2.4.dist-info/RECORD
