Metadata-Version: 2.1
Name: configfile
Version: 1.2.4
Summary: Dynamically parse and edit configuration files.
Home-page: https://github.com/kynikos/lib.py.configfile
Author: Dario Giovannetti
Author-email: dev@dariogiovannetti.net
License: MIT
Keywords: configuration parser development
Platform: UNKNOWN
Classifier: Development Status :: 4 - Beta
Classifier: Environment :: Console
Classifier: Intended Audience :: Developers
Classifier: Topic :: Software Development
Classifier: Topic :: Software Development :: Libraries :: Python Modules
Classifier: Topic :: Text Processing
Classifier: License :: OSI Approved :: MIT License
Classifier: Programming Language :: Python :: 2
Classifier: Programming Language :: Python :: 2.6
Classifier: Programming Language :: Python :: 2.7
Classifier: Programming Language :: Python :: 3
Classifier: Programming Language :: Python :: 3.6
Classifier: Programming Language :: Python :: 3.7
